{
	"configurations" : 
	[
		{
			"directories" : 
			[
				{
					"build" : ".",
					"jsonFile" : "directory-.-Release-d0094a50bb2071803777.json",
					"minimumCMakeVersion" : 
					{
						"string" : "3.8"
					},
					"projectIndex" : 0,
					"source" : ".",
					"targetIndexes" : 
					[
						0
					]
				}
			],
			"name" : "Release",
			"projects" : 
			[
				{
					"directoryIndexes" : 
					[
						0
					],
					"name" : "Graphics_PA3",
					"targetIndexes" : 
					[
						0
					]
				}
			],
			"targets" : 
			[
				{
					"directoryIndex" : 0,
					"id" : "Main::@6890427a1f51a3e7e1df",
					"jsonFile" : "target-Main-Release-4af23849371080c05966.json",
					"name" : "Main",
					"projectIndex" : 0
				}
			]
		}
	],
	"kind" : "codemodel",
	"paths" : 
	{
		"build" : "C:/Users/41449/Desktop/COMP3271/A3/Graphics_PA3_Release/out/build/x64-Release",
		"source" : "C:/Users/41449/Desktop/COMP3271/A3/Graphics_PA3_Release"
	},
	"version" : 
	{
		"major" : 2,
		"minor" : 3
	}
}
